odoo/addons/product_main_seller/README.rst
odoo/addons/product_main_seller/__init__.py
odoo/addons/product_main_seller/__manifest__.py
odoo/addons/product_main_seller/hooks.py
odoo/addons/product_main_seller/i18n/fr.po
odoo/addons/product_main_seller/i18n/it.po
odoo/addons/product_main_seller/i18n/nl.po
odoo/addons/product_main_seller/i18n/product_main_seller.pot
odoo/addons/product_main_seller/models/__init__.py
odoo/addons/product_main_seller/models/product_template.py
odoo/addons/product_main_seller/readme/CONTRIBUTORS.md
odoo/addons/product_main_seller/readme/DESCRIPTION.md
odoo/addons/product_main_seller/static/description/icon.png
odoo/addons/product_main_seller/static/description/index.html
odoo/addons/product_main_seller/static/description/product_tree_view.png
odoo/addons/product_main_seller/tests/__init__.py
odoo/addons/product_main_seller/tests/test_seller.py
odoo/addons/product_main_seller/views/view_product_product.xml
odoo/addons/product_main_seller/views/view_product_template.xml
odoo_addon_product_main_seller-18.0.1.0.0.2.dist-info/METADATA
odoo_addon_product_main_seller-18.0.1.0.0.2.dist-info/WHEEL
odoo_addon_product_main_seller-18.0.1.0.0.2.dist-info/top_level.txt
odoo_addon_product_main_seller-18.0.1.0.0.2.dist-info/RECORD
